aiow/__init__.py
aiow/__main__.py
aiow-1.2.dist-info/LICENSE
aiow-1.2.dist-info/METADATA
aiow-1.2.dist-info/WHEEL
aiow-1.2.dist-info/top_level.txt
aiow-1.2.dist-info/RECORD
