Metadata-Version: 2.1
Name: aiow
Version: 1.2
Summary: Aiohttp based wrapper.
Home-page: https://t.me/execal
Author: odi
Author-email: ivuxey@gmail.com
License: MIT
Project-URL: Source, https://github.com/vauth
Project-URL: Bug Tracker, https://t.me/feelded
Keywords: sync,async,aiohttp,proxy
Classifier: Programming Language :: Python :: 3
Classifier: License :: OSI Approved :: MIT License
Classifier: Operating System :: OS Independent
Requires-Python: >=3.5
License-File: LICENSE
Requires-Dist: PySocks
Requires-Dist: aiohttp
Requires-Dist: aiohttp-socks
